setup.cfg
setup.py
apiclient/__init__.py
apiclient/base.py
apiclient/exceptions.py
apiclient_requests.egg-info/PKG-INFO
apiclient_requests.egg-info/SOURCES.txt
apiclient_requests.egg-info/dependency_links.txt
apiclient_requests.egg-info/pbr.json
apiclient_requests.egg-info/requires.txt
apiclient_requests.egg-info/top_level.txt