Metadata-Version: 1.0
Name: apiclient-requests
Version: 0.1.1
Summary: A simple python base package for building good api clients on
Home-page: https://github.com/suraj-arya/apiclient-requests
Author: Suraj Arya
Author-email: suraj.p.arya@gmail.com
License: MIT
Platform: UNKNOWN
